ecgtools/__init__.py
ecgtools/_version.py
ecgtools/builder.py
ecgtools/parsers/__init__.py
ecgtools/parsers/cesm.py
ecgtools/parsers/cmip.py
ecgtools/parsers/observations.py
ecgtools/parsers/utilities.py
ecgtools_access-2025.10.7.dist-info/licenses/LICENSE
ecgtools_access-2025.10.7.dist-info/METADATA
ecgtools_access-2025.10.7.dist-info/WHEEL
ecgtools_access-2025.10.7.dist-info/top_level.txt
ecgtools_access-2025.10.7.dist-info/RECORD
