Metadata-Version: 2.4
Name: ecgtools-access
Version: 2025.10.7
Summary: ESM Catalog Generation Utilities. This is the ACCESS-NRI bleeding edge fork.
Maintainer-email: ACCESS-NRI <charles.turner@anu.edu.au>
License-Expression: Apache-2.0
Project-URL: Homepage, https://github.com/access-nri/ecgtools
Project-URL: Documentation, https://ecgtools.readthedocs.io/
Project-URL: Source, https://github.com/access-nri/ecgtools
Project-URL: Tracker, https://github.com/access-nri/ecgtools/issues
Keywords: ecgtools
Classifier: Development Status :: 2 - Pre-Alpha
Classifier: Natural Language :: English
Classifier: Programming Language :: Python :: 3
Classifier: Programming Language :: Python :: 3.8
Classifier: Programming Language :: Python :: 3.9
Classifier: Programming Language :: Python :: 3.10
Classifier: Topic :: Scientific/Engineering
Classifier: Operating System :: OS Independent
Classifier: Intended Audience :: Science/Research
Requires-Python: >=3.10
License-File: LICENSE
Requires-Dist: cf_xarray
Requires-Dist: joblib
Requires-Dist: netCDF4
Requires-Dist: xarray
Requires-Dist: pyyaml
Requires-Dist: pydantic>=2.0
Requires-Dist: pandas
Requires-Dist: fsspec
Requires-Dist: intake-esm-access>2025.9.11
Dynamic: license-file
